Metadata-Version: 2.1
Name: simpleclient
Version: 0.0.5
Summary: Python Simple HTTP Client
Home-page: https://github.com/nggit/simpleclient
Author: nggit
Author-email: contact@anggit.com
License: MIT
Platform: UNKNOWN
Classifier: Development Status :: 5 - Production/Stable
Classifier: Intended Audience :: Developers
Classifier: License :: OSI Approved :: MIT License
Classifier: Operating System :: OS Independent
Classifier: Topic :: System :: Networking
